<quest xmlns:xsi="http://www.w3.org/2001/XMLSchema-instance">
   <quest_desc>
      <qename>mqc21_9779_skeleton_box_key</qename>
      <qtype>mainquest</qtype>
      <qcomtype>ONCE</qcomtype>
      <qchapter>21</qchapter>
      <qid>9779</qid>
      <designer>김민정</designer>
      <qlevel>93</qlevel>
      <qdesc />
      <qdifficulty>1</qdifficulty>
      <nextqid>9780</nextqid>
      <nextqname>mqc21_9780_kairon_island</nextqname>
      <nextqnpc>n2254_geraint</nextqnpc>
      <uistyle>1</uistyle>
      <qkname mid="1"><![CDATA[Key to the Ashes]]></qkname>
      <qnpc>
         <npcid>735</npcid>
         <npcename>n735_darklair_mocha</npcename>
         <npckname>어둠의 여신관 모카</npckname>
      </qnpc>
      <qnpc>
         <npcid>2253</npcid>
         <npcename>n2253_nophee</npcename>
         <npckname>노르페</npckname>
      </qnpc>
      <qnpc>
         <npcid>2106</npcid>
         <npcename>n2106_velskud</npcename>
         <npckname>벨스커드</npckname>
      </qnpc>
      <qnpc>
         <npcid>2304</npcid>
         <npcename>n2304_geraint</npcename>
         <npckname>제레인트</npckname>
      </qnpc>
      <qnpc>
         <npcid>2254</npcid>
         <npcename>n2254_geraint</npcename>
         <npckname>제레인트</npckname>
      </qnpc>
      <qnpc>
         <npcid>1813</npcid>
         <npcename>n1813_rubinat_box</npcename>
         <npckname>의문의 장식함</npckname>
      </qnpc>
      <qnpc>
         <npcid>2265</npcid>
         <npcename>n2265_rubinat_phantom</npcename>
         <npckname>루비나트의 환영</npckname>
      </qnpc>
   </quest_desc>
   <talk_paragraph index="q_enter" />
   <talk_paragraph index="!quit" />
   <talk_paragraph index="_no_quest">
      <talk_question mid="2"><![CDATA[<html>{ui_string:1200001}</html>]]></talk_question>
   </talk_paragraph>
   <talk_paragraph index="_full_quest">
      <talk_question mid="3"><![CDATA[<html>{ui_string:1200002}</html>]]></talk_question>
   </talk_paragraph>
   <talk_paragraph index="_full_inventory">
      <talk_question mid="4"><![CDATA[<html>{ui_string:1200003}</html>]]></talk_question>
   </talk_paragraph>
   <talk_paragraph index="_daily_quest_fail">
      <talk_question mid="99998"><![CDATA[<html>{ui_string:1200004}</html>]]></talk_question>
   </talk_paragraph>
   <talk_paragraph index="_full_Qinventory">
      <talk_question mid="99999"><![CDATA[<html>{ui_string:1200005}</html>]]></talk_question>
   </talk_paragraph>
   <talk_paragraph index="n735_darklair_mocha-accepting" image="" itemindex="" portrait_left="" portrait_right="NPC_Right_Darklair_Castia.dds" center_image="">
      <talk_answer link_index="n735_darklair_mocha-accepting-a" mid="6" select_type="2" />
      <talk_question mid="5"><![CDATA[<html>$Dark Priestess Mocha$<BR>Walaupun Monolith barrier masih aman, racun dari Mistland akan terus mempengaruhi Althea.<BR>Tidak akan lama sampai keseimbangan dunia jatuh. </html>]]></talk_question>
   </talk_paragraph>
   <talk_paragraph index="n735_darklair_mocha-accepting-a" image="" itemindex="" portrait_left="" portrait_right="NPC_Right_Darklair_Castia.dds" center_image="">
      <talk_answer link_index="n735_darklair_mocha-accepting-acceptted" mid="8" select_type="3" />
      <talk_question mid="7"><![CDATA[<html>${user_nick}$<BR><FONT color=#662500>Aku akan berusaha menghentikannya.</FONT></html>]]></talk_question>
   </talk_paragraph>
   <talk_paragraph index="n735_darklair_mocha-1" image="" itemindex="" portrait_left="" portrait_right="NPC_Right_Darklair_Castia.dds" center_image="">
      <talk_answer link_index="n735_darklair_mocha-1-" mid="10" select_type="5" />
      <talk_question mid="9"><![CDATA[<html>$Dark Priestess Mocha$<BR>Terima kasih. Semoga kamu baik-baik saja di Mistland.<BR>Kekuatan Goddess akan selalu menyertaimu...</html>]]></talk_question>
   </talk_paragraph>
   <talk_paragraph index="n2253_nophee-1" image="" itemindex="" portrait_left="" portrait_right="Npc_Right_Nophee.dds" center_image="">
      <talk_answer link_index="n2253_nophee-1-a" mid="12" select_type="0"><![CDATA[<html>Sampaikan bahwa aku telah membunuh Mamon.</html>]]></talk_answer>
      <talk_answer link_index="n2253_nophee-1-b" mid="13" select_type="0"><![CDATA[<html>Bilang bahwa aku tidak pergi ke istana Mamon.</html>]]></talk_answer>
      <talk_question mid="11"><![CDATA[<html>$Norfe$<BR><FONT color=#387206>{user_nick}</FONT>, aku mencemaskanmu.<BR>Apa tadi kamu ke istana Mamon?</html>]]></talk_question>
   </talk_paragraph>
   <talk_paragraph index="n2253_nophee-1-a" image="" itemindex="" portrait_left="" portrait_right="Npc_Right_Nophee.dds" center_image="">
      <talk_answer link_index="n2253_nophee-1-c" mid="15" select_type="2" />
      <talk_question mid="14"><![CDATA[<html>$Norfe$<BR>Oh begitu. Gregory melakukan sesuatu yang tak terduga rupanya. <BR>Aku tidak menduga hal seperti itu. </html>]]></talk_question>
   </talk_paragraph>
   <talk_paragraph index="n2253_nophee-1-b" image="" itemindex="" portrait_left="" portrait_right="Npc_Right_Nophee.dds" center_image="">
      <talk_answer link_index="n2253_nophee-1-c" mid="17" select_type="2" />
      <talk_question mid="16"><![CDATA[<html>$Norfe$<BR>Ah... aku berpikir bahwa <FONT color=#387206>{user_nick}</FONT> juga ditugaskan untuk mengepung istana Mamon.<BR>Mungkin memang sebaiknya kamu tidak ke sana. Karena <FONT color=#387206>{user_nick}</FONT> harus menyimpan tenaga untuk mencari Healing Cup.<BR>Tentara kami yang mengepung istana Mamon berhasil dikalahkan oleh Grelle dan jewel milik Mamon berhasil jatuh ke tangannya..</html>]]></talk_question>
   </talk_paragraph>
   <talk_paragraph index="n2253_nophee-1-c" image="" itemindex="" portrait_left="" portrait_right="Npc_Right_Nophee.dds" center_image="">
      <talk_answer link_index="n2253_nophee-1-d" mid="19" select_type="2" />
      <talk_question mid="18"><![CDATA[<html>$Norfe$<BR>Namun, yang perlu dikuatirkan adalah Grelle yang telah menyerap kekuatan Mamon.<BR>Dia telah menyerap banyak kekuatan Child lain, namun karena impact pada Hiver tidak stabil maka kekuatannya pun menjadi tidak stabil. </html>]]></talk_question>
   </talk_paragraph>
   <talk_paragraph index="n2253_nophee-1-d" image="" itemindex="" portrait_left="" portrait_right="Npc_Right_Nophee.dds" center_image="">
      <talk_answer link_index="n2253_nophee-1-e" mid="21" select_type="2" />
      <talk_question mid="20"><![CDATA[<html>${user_nick}$<BR><FONT color=#662500>Kamu bilang Grelle mungkin membuat kesalahan?</FONT></html>]]></talk_question>
   </talk_paragraph>
   <talk_paragraph index="n2253_nophee-1-e" image="" itemindex="" portrait_left="" portrait_right="Npc_Right_Nophee.dds" center_image="">
      <talk_answer link_index="n2253_nophee-1-f" mid="23" select_type="2" />
      <talk_question mid="22"><![CDATA[<html>$Norfe$<BR>Aku tidak memiliki jawaban yang pasti, namun bila tidak menyelesaikan Jewel Harmony maka akan berbahaya bagimu.</html>]]></talk_question>
   </talk_paragraph>
   <talk_paragraph index="n2253_nophee-1-f" image="" itemindex="" portrait_left="" portrait_right="Npc_Right_Nophee.dds" center_image="">
      <talk_answer link_index="n2253_nophee-1-g" mid="25" select_type="2" />
      <talk_question mid="24"><![CDATA[<html>${user_nick}$<BR><FONT color=#662500>… apakah sudah terjerumus seperti Rubinart?</FONT></html>]]></talk_question>
   </talk_paragraph>
   <talk_paragraph index="n2253_nophee-1-g" image="" itemindex="" portrait_left="" portrait_right="Npc_Right_Nophee.dds" center_image="">
      <talk_answer link_index="n2253_nophee-1-h" mid="27" select_type="2" />
      <talk_question mid="26"><![CDATA[<html>$Norfe$<BR>Child Dragon adalah makhluk hidup biasa, sedangkan Grelle adalah seorang mutant…<BR>Mungkin bisa dilihat seperti child yang kembali semula.<BR>Dalam kasus yang lebih parah, dia tidak akan dapat mengontrol dirinya sendiri.. </html>]]></talk_question>
   </talk_paragraph>
   <talk_paragraph index="n2253_nophee-1-h" image="" itemindex="" portrait_left="" portrait_right="Npc_Right_Nophee.dds" center_image="">
      <talk_answer link_index="n2253_nophee-1-i" mid="29" select_type="2" />
      <talk_question mid="28"><![CDATA[<html>${user_nick}$<BR><FONT color=#662500>Itu…! Kita tak dapat membiarkan Grelle begitu saja!<BR>Pasti ada caranya.</FONT></html>]]></talk_question>
   </talk_paragraph>
   <talk_paragraph index="n2253_nophee-1-i" image="" itemindex="" portrait_left="" portrait_right="Npc_Right_Nophee.dds" center_image="">
      <talk_answer link_index="n2253_nophee-1-j" mid="31" select_type="2" />
      <talk_question mid="30"><![CDATA[<html>$Norfe$<BR>Saat ini kita tidak dapat melakukan apa-apa terhadap Child's Jewel Harmony.<BR>Grelle harus menang melawan kekuatan itu sendiri.</html>]]></talk_question>
   </talk_paragraph>
   <talk_paragraph index="n2253_nophee-1-j" image="" itemindex="" portrait_left="" portrait_right="Npc_Right_Nophee.dds" center_image="">
      <talk_answer link_index="n2253_nophee-2" mid="33" select_type="2" />
      <talk_question mid="32"><![CDATA[<html>$Norfe$<BR>Ah... Lalu, Grelle bilang dia sudah kembali setelah mencari informasi tentang Healing Cup dari Monolith.<BR>Alangkah baiknya bila kamu pergi menemui Gerraint di Monollith terlebih dahulu.</html>]]></talk_question>
   </talk_paragraph>
   <talk_paragraph index="n2253_nophee-2" image="" itemindex="" portrait_left="" portrait_right="Npc_Right_Nophee.dds" center_image="">
      <talk_answer link_index="n2253_nophee-2-change_map_chk" mid="35" select_type="0"><![CDATA[<html>Baiklah.</html>]]></talk_answer>
      <talk_answer link_index="n2253_nophee-2-b" mid="36" select_type="0"><![CDATA[<html>Tunggu sebentar ya.</html>]]></talk_answer>
      <talk_question mid="34"><![CDATA[<html>$Norfe$<BR>Gerraint telah menunggumu di Monolith.</html>]]></talk_question>
   </talk_paragraph>
   <talk_paragraph index="n2253_nophee-2-a" image="" itemindex="" portrait_left="" portrait_right="Npc_Right_Nophee.dds" center_image="">
      <talk_answer link_index="n2253_nophee-2-b" mid="38" select_type="5" />
      <talk_question mid="37"><![CDATA[<html>$Norfe$<BR>Tidak dapat memasuki Monolith saat berada di dalam party.<BR><BR><FONT color=#7e12d2>※Quest tidak dapat dilakukan saat berada di dalam party.</FONT></html>]]></talk_question>
   </talk_paragraph>
   <talk_paragraph index="n2253_nophee-2-b" image="" itemindex="" portrait_left="" portrait_right="Npc_Right_Nophee.dds" center_image="">
      <talk_answer link_index="n2253_nophee-2-" mid="40" select_type="5" />
      <talk_question mid="39"><![CDATA[<html>$Norfe$<BR>Aku mengerti. Bila sudah siap, datanglah kembali.</html>]]></talk_question>
   </talk_paragraph>
   <talk_paragraph index="n2106_velskud-2" image="" itemindex="" portrait_left="" portrait_right="Npc_Right_Velskud_Human.dds" center_image="">
      <talk_answer link_index="n2106_velskud-2-" mid="112" select_type="5" />
      <talk_question mid="41"><![CDATA[<html>$Velskud$<BR>Pergilah segera, kamu akan sakit bila terus berada di sini.</html>]]></talk_question>
   </talk_paragraph>
   <talk_paragraph index="n2304_geraint-2" image="" itemindex="" portrait_left="" portrait_right="NPC_Right_geraint_Kid.dds" center_image="">
      <talk_answer link_index="n2304_geraint-2-a" mid="113" select_type="2" />
      <talk_question mid="42"><![CDATA[<html>$Gerraint$<BR>Kenapa baru muncul sekarang?<BR>Aku sudah menunggu dari tadi!</html>]]></talk_question>
   </talk_paragraph>
   <talk_paragraph index="n2304_geraint-2-a" image="" itemindex="" portrait_left="" portrait_right="NPC_Right_geraint_Kid.dds" center_image="">
      <talk_answer link_index="n2304_geraint-2-b" mid="114" select_type="2" />
      <talk_question mid="43"><![CDATA[<html>${user_nick}$<BR><FONT color=#662500>Kan aku juga banyak kerjaan!</FONT></html>]]></talk_question>
   </talk_paragraph>
   <talk_paragraph index="n2304_geraint-2-b" image="" itemindex="" portrait_left="" portrait_right="NPC_Right_geraint_Kid.dds" center_image="">
      <talk_answer link_index="n2304_geraint-2-c" mid="115" select_type="2" />
      <talk_question mid="44"><![CDATA[<html>$Gerraint$<BR>Lalu si Grelle itu pasti berulah lagi.<BR><FONT color=#7e12d2>(Entah kenapa Gerraint nampak kesal.)</FONT></html>]]></talk_question>
   </talk_paragraph>
   <talk_paragraph index="n2304_geraint-2-c" image="" itemindex="" portrait_left="" portrait_right="NPC_Right_geraint_Kid.dds" center_image="">
      <talk_answer link_index="n2304_geraint-2-d" mid="116" select_type="2" />
      <talk_question mid="45"><![CDATA[<html>${user_nick}$<BR><FONT color=#662500>Jadi kamu marah-marah karena aku bersama Grelle?<BR>Bukannya kamu yang bilang mau ke Monolith!</FONT></html>]]></talk_question>
   </talk_paragraph>
   <talk_paragraph index="n2304_geraint-2-d" image="" itemindex="" portrait_left="" portrait_right="NPC_Right_geraint_Kid.dds" center_image="">
      <talk_answer link_index="n2304_geraint-2-e" mid="117" select_type="2" />
      <talk_question mid="46"><![CDATA[<html>$Gerraint$<BR>Siapa yang marah-marah!<BR>Aku hanya kesal karena aku harus berduaan dengan Velskud.<BR><FONT color=#7e12d2>(Velskud pun melirik Gerraint dengan kesal)</FONT></html>]]></talk_question>
   </talk_paragraph>
   <talk_paragraph index="n2304_geraint-2-e" image="" itemindex="" portrait_left="" portrait_right="NPC_Right_geraint_Kid.dds" center_image="">
      <talk_answer link_index="n2304_geraint-2-f" mid="118" select_type="2" />
      <talk_question mid="47"><![CDATA[<html>${user_nick}$<BR><FONT color=#662500>Lalu apa sudah ada petunjuk tentang Healing Cup?</FONT></html>]]></talk_question>
   </talk_paragraph>
   <talk_paragraph index="n2304_geraint-2-f" image="" itemindex="" portrait_left="" portrait_right="NPC_Right_geraint_Kid.dds" center_image="">
      <talk_answer link_index="n2304_geraint-2-g" mid="119" select_type="2" />
      <talk_question mid="48"><![CDATA[<html>$Gerraint$<BR>Hmm… aku tidak tahu apa ini informasi yang berguna…<BR>Tapi aku menemukan sesuatu.<BR><FONT color=#7e12d2>(Gerraint mengeluarkan sesuatu)</FONT></html>]]></talk_question>
   </talk_paragraph>
   <talk_paragraph index="n2304_geraint-2-g" image="" itemindex="" portrait_left="" portrait_right="NPC_Right_geraint_Kid.dds" center_image="">
      <talk_answer link_index="n2304_geraint-2-h" mid="120" select_type="2" />
      <talk_question mid="49"><![CDATA[<html>$Gerraint$<BR>Ini. Aku tidak tahu apa ini, tapi ini sepertinya bukan benda yang seharusnya berada di Monolith.<BR>Aku merasakan kekuatan Althea walau hanya sedikit.</html>]]></talk_question>
   </talk_paragraph>
   <talk_paragraph index="n2304_geraint-2-h" image="" itemindex="" portrait_left="" portrait_right="NPC_Right_geraint_Kid.dds" center_image="">
      <talk_answer link_index="n2304_geraint-2-i" mid="121" select_type="2" />
      <talk_question mid="50"><![CDATA[<html>${user_nick}$<BR><FONT color=#662500>Ini...! <BR>(Aku merasakan energi yang sama dari Meriendel.)</FONT></html>]]></talk_question>
   </talk_paragraph>
   <talk_paragraph index="n2304_geraint-2-i" image="" itemindex="" portrait_left="" portrait_right="NPC_Right_geraint_Kid.dds" center_image="">
      <talk_answer link_index="n2304_geraint-2-j" mid="122" select_type="2" />
      <talk_question mid="51"><![CDATA[<html>${user_nick}$<BR><FONT color=#662500>Ini pastilah pendant yang dimiliki oleh Meriendel!<BR>Aku melihatnya mati di Monolith. </FONT></html>]]></talk_question>
   </talk_paragraph>
   <talk_paragraph index="n2304_geraint-2-j" image="" itemindex="" portrait_left="" portrait_right="NPC_Right_geraint_Kid.dds" center_image="">
      <talk_answer link_index="n2304_geraint-2-k" mid="123" select_type="2" />
      <talk_question mid="52"><![CDATA[<html>$Gerraint$<BR>Jadi… ini benda milik Meriendel?</html>]]></talk_question>
   </talk_paragraph>
   <talk_paragraph index="n2304_geraint-2-k" image="" itemindex="" portrait_left="" portrait_right="Npc_Right_Velskud_Human.dds" center_image="">
      <talk_answer link_index="n2304_geraint-2-l" mid="124" select_type="2" />
      <talk_question mid="53"><![CDATA[<html>$Velskud$<BR><FONT color=#7e12d2>(Velskud yang dari tadi diam, ikut menimpali.)</FONT><BR>Aku tidak mengerti.</html>]]></talk_question>
   </talk_paragraph>
   <talk_paragraph index="n2304_geraint-2-l" image="" itemindex="" portrait_left="NPC_Left_geraint_Kid.dds" portrait_right="" center_image="">
      <talk_answer link_index="n2304_geraint-2-m" mid="125" select_type="2" />
      <talk_question mid="54"><![CDATA[<html>$Gerraint$<BR>Apanya?</html>]]></talk_question>
   </talk_paragraph>
   <talk_paragraph index="n2304_geraint-2-m" image="" itemindex="" portrait_left="" portrait_right="Npc_Right_Velskud_Human.dds" center_image="">
      <talk_answer link_index="n2304_geraint-2-n" mid="126" select_type="2" />
      <talk_question mid="55"><![CDATA[<html>$Velskud$<BR>Bila memang Meriendel mati di Monolith ini, bagaimana mungkin Rubinart memiliki Urn miliknya itu?</html>]]></talk_question>
   </talk_paragraph>
   <talk_paragraph index="n2304_geraint-2-n" image="" itemindex="" portrait_left="" portrait_right="Npc_Right_Velskud_Human.dds" center_image="">
      <talk_answer link_index="n2304_geraint-2-o" mid="127" select_type="2" />
      <talk_question mid="56"><![CDATA[<html>${user_nick}$<BR><FONT color=#662500>Benar juga… menurut ingatanku… Meriendel mati setelah meninggalkan pendantnya kepada Rubinart.</FONT></html>]]></talk_question>
   </talk_paragraph>
   <talk_paragraph index="n2304_geraint-2-o" image="" itemindex="" portrait_left="" portrait_right="Npc_Right_Velskud_Human.dds" center_image="">
      <talk_answer link_index="n2304_geraint-2-p" mid="128" select_type="2" />
      <talk_question mid="57"><![CDATA[<html>$Velskud$<BR>Rubinart harus menjaga Mistland's Barrier, karena itu dia tak dapat kembali ke Monolith.<BR>Jadi Meriendel's Urn itu...</html>]]></talk_question>
   </talk_paragraph>
   <talk_paragraph index="n2304_geraint-2-p" image="" itemindex="" portrait_left="NPC_Left_geraint_Kid.dds" portrait_right="" center_image="">
      <talk_answer link_index="n2304_geraint-2-q" mid="129" select_type="2" />
      <talk_question mid="58"><![CDATA[<html>$Gerraint$<BR>Jadi itu palsu?? Tapi buat apa membuat barang palsu seperti ini?</html>]]></talk_question>
   </talk_paragraph>
   <talk_paragraph index="n2304_geraint-2-q" image="" itemindex="" portrait_left="" portrait_right="Npc_Right_Velskud_Human.dds" center_image="">
      <talk_answer link_index="n2304_geraint-2-r" mid="130" select_type="2" />
      <talk_question mid="59"><![CDATA[<html>$Velskud$<BR>Dasar dragon noob.<BR><FONT color=#7e12d2>(Gerraint pun kesal mendengar perkataan Velskud itu.)</FONT></html>]]></talk_question>
   </talk_paragraph>
   <talk_paragraph index="n2304_geraint-2-r" image="" itemindex="" portrait_left="" portrait_right="Npc_Right_Velskud_Human.dds" center_image="">
      <talk_answer link_index="n2304_geraint-2-s" mid="131" select_type="2" />
      <talk_question mid="60"><![CDATA[<html>${user_nick}$<BR><FONT color=#662500>Tentunya pasti karena ada sebuah rahasia yang harus disembunyikan tentang Urn.<BR>Rubinart berharap bahwa Healing Cup tidak diketahui oleh dunia ini.</FONT></html>]]></talk_question>
   </talk_paragraph>
   <talk_paragraph index="n2304_geraint-2-s" image="" itemindex="" portrait_left="NPC_Left_geraint_Kid.dds" portrait_right="" center_image="">
      <talk_answer link_index="n2304_geraint-2-t" mid="132" select_type="2" />
      <talk_question mid="61"><![CDATA[<html>$Gerraint$<BR>Tapi aku mencoba membuka kotak itu, dan tidak terbuka sama sekali.<BR>Sepertinya memerlukan sebuah kunci.</html>]]></talk_question>
   </talk_paragraph>
   <talk_paragraph index="n2304_geraint-2-t" image="" itemindex="" portrait_left="" portrait_right="Npc_Right_Velskud_Human.dds" center_image="">
      <talk_answer link_index="n2304_geraint-2-u" mid="133" select_type="2" />
      <talk_question mid="62"><![CDATA[<html>$Velskud$<BR>Rahasia itu adalah kunci untuk membuka kotak itu yang berasal dari Meriendel's Urn.</html>]]></talk_question>
   </talk_paragraph>
   <talk_paragraph index="n2304_geraint-2-u" image="" itemindex="" portrait_left="" portrait_right="Npc_Right_Velskud_Human.dds" center_image="">
      <talk_answer link_index="n2304_geraint-2-v" mid="134" select_type="2" />
      <talk_question mid="63"><![CDATA[<html>${user_nick}$<BR><FONT color=#662500>Jadi peninggalan dari Meriendel ternyata adalah sebuah kunci.</FONT></html>]]></talk_question>
   </talk_paragraph>
   <talk_paragraph index="n2304_geraint-2-v" image="" itemindex="" portrait_left="" portrait_right="Npc_Right_Velskud_Human.dds" center_image="">
      <talk_answer link_index="n2304_geraint-2-w" mid="135" select_type="2" />
      <talk_question mid="64"><![CDATA[<html>$Velskud$<BR>Aku lebih baik dibandingkan dragon noob ini.</html>]]></talk_question>
   </talk_paragraph>
   <talk_paragraph index="n2304_geraint-2-w" image="" itemindex="" portrait_left="NPC_Left_geraint_Kid.dds" portrait_right="" center_image="">
      <talk_answer link_index="n2304_geraint-3" mid="136" select_type="2" />
      <talk_question mid="65"><![CDATA[<html>$Gerraint$<BR>Grrr! Intinya aku kembali membawa kunci untuk mencari Healing Cup bukan!<BR>Jangan bertele-tele lagi di sini, ayo kita segera mencari Urn atau apapun itu!</html>]]></talk_question>
   </talk_paragraph>
   <talk_paragraph index="n2253_nophee-3" image="" itemindex="" portrait_left="" portrait_right="Npc_Right_Nophee.dds" center_image="">
      <talk_answer link_index="n2253_nophee-3-" mid="137" select_type="5" />
      <talk_question mid="66"><![CDATA[<html>$Norfe$<BR>Sudahkah bertemu dengan Gerraint?<BR>Sepertinya dia berlari menuju ke Rubinart's Hideout…</html>]]></talk_question>
   </talk_paragraph>
   <talk_paragraph index="n2254_geraint-3" image="" itemindex="" portrait_left="" portrait_right="NPC_Right_geraint_Kid.dds" center_image="">
      <talk_answer link_index="n2254_geraint-3-a" mid="138" select_type="2" />
      <talk_question mid="67"><![CDATA[<html>$Gerraint$<BR>Aku akan melaporkan semua kejadian itu di sini, jadi kamu bukalah Urn dengan benda ini dan kembalilah kepadaku.</html>]]></talk_question>
   </talk_paragraph>
   <talk_paragraph index="n2254_geraint-3-a" image="" itemindex="" portrait_left="" portrait_right="NPC_Right_geraint_Kid.dds" center_image="">
      <talk_answer link_index="n2254_geraint-3-" mid="139" select_type="5" />
      <talk_question mid="68"><![CDATA[<html>${user_nick}$<BR><FONT color=#662500>Baiklah.<BR>(Menerima peninggalan Meriendel dari Gerraint.)</FONT></html>]]></talk_question>
   </talk_paragraph>
   <talk_paragraph index="n2254_geraint-4" image="" itemindex="" portrait_left="" portrait_right="NPC_Right_geraint_Kid.dds" center_image="">
      <talk_answer link_index="n2254_geraint-4-" mid="140" select_type="5" />
      <talk_question mid="69"><![CDATA[<html>$Gerraint$<BR>Kamu sudah membuka Urn di Rubinart's Hideout?</html>]]></talk_question>
   </talk_paragraph>
   <talk_paragraph index="n1813_rubinat_box-4" image="" itemindex="" portrait_left="" portrait_right="" center_image="">
      <talk_answer link_index="n1813_rubinat_box-4-" mid="141" select_type="5" />
      <talk_question mid="70"><![CDATA[<html>$Meriendel's Urn$<BR><FONT color=#7e12d2>(Kotak ini terbuka dan kosong.)</FONT></html>]]></talk_question>
   </talk_paragraph>
   <talk_paragraph index="n2265_rubinat_phantom-4" image="" itemindex="" portrait_left="" portrait_right="NPC_Right_rubinat.dds" center_image="">
      <talk_answer link_index="n2265_rubinat_phantom-4-a" mid="142" select_type="2" />
      <talk_question mid="71"><![CDATA[<html>$Rubinart Phantasm${sound:npc_Rubinart_9779_qu_01.ogg}<BR>Padahal aku berharap kalian tidak membuka Urn itu…</html>]]></talk_question>
   </talk_paragraph>
   <talk_paragraph index="n2265_rubinat_phantom-4-a" image="" itemindex="" portrait_left="" portrait_right="NPC_Right_rubinat.dds" center_image="">
      <talk_answer link_index="n2265_rubinat_phantom-4-b" mid="143" select_type="2" />
      <talk_question mid="72"><![CDATA[<html>${user_nick}$<BR><FONT color=#662500>Memang Urn ini tidak berisi peninggalan Meriendel.</FONT></html>]]></talk_question>
   </talk_paragraph>
   <talk_paragraph index="n2265_rubinat_phantom-4-b" image="" itemindex="" portrait_left="" portrait_right="NPC_Right_rubinat.dds" center_image="">
      <talk_answer link_index="n2265_rubinat_phantom-4-c" mid="144" select_type="2" />
      <talk_question mid="73"><![CDATA[<html>$Rubinart Phantasm$<BR>Betul, aku sudah meninggalkan pesan tentang Healing Cup di dalam Urn ini.</html>]]></talk_question>
   </talk_paragraph>
   <talk_paragraph index="n2265_rubinat_phantom-4-c" image="" itemindex="" portrait_left="" portrait_right="NPC_Right_rubinat.dds" center_image="">
      <talk_answer link_index="n2265_rubinat_phantom-4-d" mid="145" select_type="2" />
      <talk_question mid="74"><![CDATA[<html>${user_nick}$<BR><FONT color=#662500>Mengapa kamu berharap bahwa Healing Cup tidak ditemukan?<BR>Healing Cup akan memurnikanmu dan juga melindungi Althea, bukan?</FONT></html>]]></talk_question>
   </talk_paragraph>
   <talk_paragraph index="n2265_rubinat_phantom-4-d" image="" itemindex="" portrait_left="" portrait_right="NPC_Right_rubinat.dds" center_image="">
      <talk_answer link_index="n2265_rubinat_phantom-4-e" mid="146" select_type="2" />
      <talk_question mid="75"><![CDATA[<html>$Rubinart Phantasm$<BR>Betul. Tapi itu juga salah.</html>]]></talk_question>
   </talk_paragraph>
   <talk_paragraph index="n2265_rubinat_phantom-4-e" image="" itemindex="" portrait_left="" portrait_right="NPC_Right_rubinat.dds" center_image="">
      <talk_answer link_index="n2265_rubinat_phantom-4-f" mid="147" select_type="2" />
      <talk_question mid="76"><![CDATA[<html>${user_nick}$<BR><FONT color=#662500>Apa maksudnya?</FONT></html>]]></talk_question>
   </talk_paragraph>
   <talk_paragraph index="n2265_rubinat_phantom-4-f" image="" itemindex="" portrait_left="" portrait_right="NPC_Right_rubinat.dds" center_image="">
      <talk_answer link_index="n2265_rubinat_phantom-4-g" mid="148" select_type="2" />
      <talk_question mid="77"><![CDATA[<html>$Rubinart Phantasm$<BR>Aku berpikir bahwa itu adalah cara terakhir. Aku berharap tidak ada seorangpun dapat menemukan Healing Cup… jadi aku hanya akan menggunakan cara itu bila benar-benar tidak ada lagi cara lain.</html>]]></talk_question>
   </talk_paragraph>
   <talk_paragraph index="n2265_rubinat_phantom-4-g" image="" itemindex="" portrait_left="" portrait_right="NPC_Right_rubinat.dds" center_image="">
      <talk_answer link_index="n2265_rubinat_phantom-4-h" mid="149" select_type="2" />
      <talk_question mid="78"><![CDATA[<html>$Rubinart Phantasm${sound:npc_Rubinart_9779_qu_02.ogg}<BR>Bila kalian sudah membuka Urn maka kalian tidak punya pilihan lain selain menemukan Healing Cup itu <BR>dan aku sudah terjerumus bukan?</html>]]></talk_question>
   </talk_paragraph>
   <talk_paragraph index="n2265_rubinat_phantom-4-h" image="" itemindex="" portrait_left="" portrait_right="NPC_Right_rubinat.dds" center_image="">
      <talk_answer link_index="n2265_rubinat_phantom-4-i" mid="150" select_type="2" />
      <talk_question mid="79"><![CDATA[<html>${user_nick}$<BR><FONT color=#662500>Baik. Rubinart sudah terjerumus sehingga untuk memecahkan kekuatan dari Goddess Vestinel, mau tidak mau harus menggunakan Healing Cup.</FONT></html>]]></talk_question>
   </talk_paragraph>
   <talk_paragraph index="n2265_rubinat_phantom-4-i" image="" itemindex="" portrait_left="" portrait_right="NPC_Right_rubinat.dds" center_image="">
      <talk_answer link_index="n2265_rubinat_phantom-4-j" mid="151" select_type="2" />
      <talk_question mid="80"><![CDATA[<html>$Rubinart Phantasm$<BR>Betul… aku minta maaf karena telah menambah bebanmu.<BR>Tapi aku percaya kepadamu. Karena aku merasakan spirit dari Argenta dan juga orang itu.</html>]]></talk_question>
   </talk_paragraph>
   <talk_paragraph index="n2265_rubinat_phantom-4-j" image="" itemindex="" portrait_left="" portrait_right="NPC_Right_rubinat.dds" center_image="">
      <talk_answer link_index="n2265_rubinat_phantom-4-k" mid="152" select_type="2" />
      <talk_question mid="81"><![CDATA[<html>${user_nick}$<BR><FONT color=#662500>Apa maksudmu?</FONT></html>]]></talk_question>
   </talk_paragraph>
   <talk_paragraph index="n2265_rubinat_phantom-4-k" image="" itemindex="" portrait_left="" portrait_right="NPC_Right_rubinat.dds" center_image="">
      <talk_answer link_index="n2265_rubinat_phantom-4-l" mid="153" select_type="2" />
      <talk_question mid="82"><![CDATA[<html>$Rubinart Phantasm$<BR>Aku ingin mengobrol lebih lama, tapi sayangnya waktuku tidak banyak.<BR>Aku juga tidak tahu persis lokasi dari Healing Cup. Tapi petunjuk tentang Healing Cup, dapat kamu temukan di Kairon Island…</html>]]></talk_question>
   </talk_paragraph>
   <talk_paragraph index="n2265_rubinat_phantom-4-l" image="" itemindex="" portrait_left="" portrait_right="NPC_Right_rubinat.dds" center_image="">
      <talk_answer link_index="n2265_rubinat_phantom-4-m" mid="154" select_type="2" />
      <talk_question mid="83"><![CDATA[<html>${user_nick}$<BR><FONT color=#662500>(Kata-kata Rubinart's semakin menghilang.)<BR>Rubinart! Hei! Coba ulangi lagi! Aku harus pergi ke Kairon Island?</FONT></html>]]></talk_question>
   </talk_paragraph>
   <talk_paragraph index="n2265_rubinat_phantom-4-m" image="" itemindex="" portrait_left="" portrait_right="NPC_Right_rubinat.dds" center_image="">
      <talk_answer link_index="n2265_rubinat_phantom-4-n" mid="155" select_type="2" />
      <talk_question mid="84"><![CDATA[<html>$Rubinart Phantasm$<BR>… Kairon Island…  ….peninggalan….<BR>Mist…. …. </html>]]></talk_question>
   </talk_paragraph>
   <talk_paragraph index="n2265_rubinat_phantom-4-n" image="" itemindex="" portrait_left="" portrait_right="NPC_Right_rubinat.dds" center_image="">
      <talk_answer link_index="n2265_rubinat_phantom-4-o" mid="156" select_type="2" />
      <talk_question mid="85"><![CDATA[<html>${user_nick}$<BR><FONT color=#662500>Rubinart!</FONT></html>]]></talk_question>
   </talk_paragraph>
   <talk_paragraph index="n2265_rubinat_phantom-4-o" image="" itemindex="" portrait_left="" portrait_right="NPC_Right_rubinat.dds" center_image="">
      <talk_answer link_index="n2265_rubinat_phantom-4-" mid="157" select_type="5" />
      <talk_question mid="86"><![CDATA[<html>$Rubinart Phantasm${sound:npc_Rubinart_9779_qu_03.ogg}<BR>….kan….menung…. <BR>….di sana.</html>]]></talk_question>
   </talk_paragraph>
   <talk_paragraph index="n1813_rubinat_box-5" image="" itemindex="" portrait_left="" portrait_right="" center_image="">
      <talk_answer link_index="n1813_rubinat_box-5-" mid="158" select_type="5" />
      <talk_question mid="87"><![CDATA[<html>$Meriendel's Urn$<BR>
<FONT color=#7e12d2>(Kotak yang terbuka itu kosong)</FONT></html>]]></talk_question>
   </talk_paragraph>
   <talk_paragraph index="n2254_geraint-5" image="" itemindex="" portrait_left="" portrait_right="NPC_Right_geraint_Kid.dds" center_image="">
      <talk_answer link_index="n2254_geraint-5-a" mid="159" select_type="2" />
      <talk_question mid="88"><![CDATA[<html>$Gerraint$<BR>Sudah membuka Urn?<BR>Isinya apa?</html>]]></talk_question>
   </talk_paragraph>
   <talk_paragraph index="n2254_geraint-5-a" image="" itemindex="" portrait_left="" portrait_right="NPC_Right_geraint_Kid.dds" center_image="">
      <talk_answer link_index="n2254_geraint-5-b" mid="160" select_type="2" />
      <talk_question mid="89"><![CDATA[<html>${user_nick}$<BR><FONT color=#662500>Tidak ada isinya… <BR>Hanya ada tertinggal pesan dari Rubinart di dalam Urn itu.</FONT></html>]]></talk_question>
   </talk_paragraph>
   <talk_paragraph index="n2254_geraint-5-b" image="" itemindex="" portrait_left="" portrait_right="NPC_Right_geraint_Kid.dds" center_image="">
      <talk_answer link_index="n2254_geraint-5-c" mid="161" select_type="4" />
      <talk_question mid="90"><![CDATA[<html>$Quest Reward$</html>]]></talk_question>
   </talk_paragraph>
   <talk_paragraph index="n2254_geraint-5-c" image="" itemindex="" portrait_left="" portrait_right="NPC_Right_geraint_Kid.dds" center_image="">
      <talk_answer link_index="n2254_geraint-5-!next" mid="162" select_type="2" />
      <talk_question mid="91"><![CDATA[<html>$Gerraint$<BR>Apa? Jadi orang itu tahu tentang lokasi Healing Cup?<BR><FONT color=#7e12d2>(Sepertinya Gerraint dan Velskud saling gak nyambung…)</FONT></html>]]></talk_question>
   </talk_paragraph>
   <talk_paragraph index="n2265_rubinat_phantom-5" image="" itemindex="" portrait_left="" portrait_right="NPC_Right_rubinat.dds" center_image="">
      <talk_answer link_index="n2265_rubinat_phantom-5-" mid="164" select_type="5" />
      <talk_question mid="163"><![CDATA[<html>$Rubinart Phantasm$<BR>
........</html>]]></talk_question>
   </talk_paragraph>
   <talk_paragraph index="n1813_rubinat_box-6" image="" itemindex="" portrait_left="" portrait_right="" center_image="">
      <talk_answer link_index="n1813_rubinat_box-6-" mid="172" select_type="0"><![CDATA[<html>Membuka Urn menggunakan peninggalan Meriendel.</html>]]></talk_answer>
      <talk_question mid="171"><![CDATA[<html>$Meriendel's Urn$<BR><FONT color=#7e12d2>(Kotak itu tertutup rapat.)</FONT></html>]]></talk_question>
   </talk_paragraph>
   <talk_paragraph index="n2254_geraint-6" image="" itemindex="" portrait_left="" portrait_right="NPC_Right_geraint_Kid.dds" center_image="">
      <talk_question mid="173"><![CDATA[<html>$Gerraint$<BR>Sudahkah kau membuka Urn yang berada di Rubinart's Hideout?</html>]]></talk_question>
   </talk_paragraph>
   <qstep_change qstep="accepting">
      <comment />
      <conditions />
      <executions>
         <exe type="setquest">9779</exe>
         <exe type="talk" npc="n735_darklair_mocha">1</exe>
      </executions>
   </qstep_change>
   <qstep_change qstep="1">
      <comment />
      <conditions />
      <executions>
         <exe type="setstep">2</exe>
         <exe type="setjornal">2</exe>
      </executions>
   </qstep_change>
   <qstep_change qstep="2">
      <comment />
      <conditions>
         <chk type="custom">api_user_IsPartymember(userObjID) == 0</chk>
      </conditions>
      <executions>
         <exe type="setstep">3</exe>
         <exe type="setjornal">3</exe>
         <exe type="conexe" true="3" false="4">0</exe>
         <exe type="custom">api_user_ChangeMap(userObjID,13526,1);</exe>
         <exe type="talk" npc="n2253_nophee">a</exe>
      </executions>
   </qstep_change>
   <qstep_change qstep="3">
      <comment />
      <conditions />
      <executions>
         <exe type="setstep">6</exe>
         <exe type="setjornal">4</exe>
      </executions>
   </qstep_change>
   <qstep_change qstep="4">
      <comment />
      <conditions />
      <executions>
         <exe type="setstep">5</exe>
         <exe type="setjornal">6</exe>
      </executions>
   </qstep_change>
   <qstep_change qstep="5">
      <comment />
      <conditions />
      <executions>
         <exe type="recompense">97790,,,,,,,,,</exe>
         <exe type="complete" true="">9779</exe>
      </executions>
   </qstep_change>
   <qstep_change qstep="6">
      <comment />
      <conditions />
      <executions>
         <exe type="setstep">4</exe>
         <exe type="setjornal">5</exe>
      </executions>
   </qstep_change>
   <exelink qstep="accepting" npc="n735_darklair_mocha" sub="acceptted">0,1</exelink>
   <exelink qstep="1" npc="n2253_nophee" sub="c" />
   <exelink qstep="1" npc="n2253_nophee" sub="c" />
   <exelink qstep="1" npc="n2253_nophee" sub="d" />
   <exelink qstep="1" npc="n2253_nophee" sub="e" />
   <exelink qstep="1" npc="n2253_nophee" sub="f" />
   <exelink qstep="1" npc="n2253_nophee" sub="g" />
   <exelink qstep="1" npc="n2253_nophee" sub="h" />
   <exelink qstep="1" npc="n2253_nophee" sub="i" />
   <exelink qstep="1" npc="n2253_nophee" sub="j" />
   <exelink qstep="1" npc="n2253_nophee" sub="2">0,1</exelink>
   <exelink qstep="2" npc="n2253_nophee" sub="change_map_chk">2</exelink>
   <exelink qstep="2" npc="n2253_nophee" sub="b" />
   <exelink qstep="2" npc="n2253_nophee" sub="" />
   <exelink qstep="2" npc="n2304_geraint" sub="b" />
   <exelink qstep="2" npc="n2304_geraint" sub="c" />
   <exelink qstep="2" npc="n2304_geraint" sub="d" />
   <exelink qstep="2" npc="n2304_geraint" sub="e" />
   <exelink qstep="2" npc="n2304_geraint" sub="f" />
   <exelink qstep="2" npc="n2304_geraint" sub="g" />
   <exelink qstep="2" npc="n2304_geraint" sub="h" />
   <exelink qstep="2" npc="n2304_geraint" sub="i" />
   <exelink qstep="2" npc="n2304_geraint" sub="j" />
   <exelink qstep="2" npc="n2304_geraint" sub="k" />
   <exelink qstep="2" npc="n2304_geraint" sub="l" />
   <exelink qstep="2" npc="n2304_geraint" sub="m" />
   <exelink qstep="2" npc="n2304_geraint" sub="n" />
   <exelink qstep="2" npc="n2304_geraint" sub="o" />
   <exelink qstep="2" npc="n2304_geraint" sub="p" />
   <exelink qstep="2" npc="n2304_geraint" sub="q" />
   <exelink qstep="2" npc="n2304_geraint" sub="r" />
   <exelink qstep="2" npc="n2304_geraint" sub="s" />
   <exelink qstep="2" npc="n2304_geraint" sub="t" />
   <exelink qstep="2" npc="n2304_geraint" sub="u" />
   <exelink qstep="2" npc="n2304_geraint" sub="v" />
   <exelink qstep="2" npc="n2304_geraint" sub="w" />
   <exelink qstep="2" npc="n2304_geraint" sub="3">0,1</exelink>
   <exelink qstep="3" npc="n2254_geraint" sub="a">0,1</exelink>
   <exelink qstep="3" npc="n2254_geraint" sub="" />
   <exelink qstep="4" npc="n2265_rubinat_phantom" sub="b" />
   <exelink qstep="4" npc="n2265_rubinat_phantom" sub="c" />
   <exelink qstep="4" npc="n2265_rubinat_phantom" sub="d" />
   <exelink qstep="4" npc="n2265_rubinat_phantom" sub="e" />
   <exelink qstep="4" npc="n2265_rubinat_phantom" sub="f" />
   <exelink qstep="4" npc="n2265_rubinat_phantom" sub="g" />
   <exelink qstep="4" npc="n2265_rubinat_phantom" sub="h" />
   <exelink qstep="4" npc="n2265_rubinat_phantom" sub="i" />
   <exelink qstep="4" npc="n2265_rubinat_phantom" sub="j" />
   <exelink qstep="4" npc="n2265_rubinat_phantom" sub="k" />
   <exelink qstep="4" npc="n2265_rubinat_phantom" sub="l" />
   <exelink qstep="4" npc="n2265_rubinat_phantom" sub="m" />
   <exelink qstep="4" npc="n2265_rubinat_phantom" sub="n" />
   <exelink qstep="4" npc="n2265_rubinat_phantom" sub="o">0,1</exelink>
   <exelink qstep="4" npc="n2265_rubinat_phantom" sub="" />
   <exelink qstep="5" npc="n2254_geraint" sub="b">0</exelink>
   <exelink qstep="5" npc="n2254_geraint" sub="c">1</exelink>
   <exelink qstep="5" npc="n2254_geraint" sub="!next" />
   <exelink qstep="6" npc="n1813_rubinat_box" sub="">0,1</exelink>
   <journal_data recompense="97790" quest_title="유골함의 열쇠" chapterid="21" quest_level="93" quest_mark_type="1" use_item_list="">
      <journal index="1">
         <contents_image>QN_Nophee.dds</contents_image>
         <destination_pos>54,n2253</destination_pos>
         <destination_mode>custom:</destination_mode>
         <statemark_npcid>2253</statemark_npcid>
         <statemark_type>2</statemark_type>
         <trigger_string />
         <maptool_index />
         <title mid="92"><![CDATA[Merkha City's Norfe.]]></title>
         <contents mid="93"><![CDATA[<html>Norfe bersama dengan para pengungsi dari Radames telah mengungsi ke Merkha. Temuilah Norfe untuk membicarakan tentang rencana berikutnya.<BR><BR><FONT color=#086171>Heart of Merkha</FONT><FONT color=#a82424> - Norfe</FONT></html>]]></contents>
         <destination mid="94"><![CDATA[Pergilah ke Heart of Merkha dan bicara dengan Norfe]]></destination>
         <todo_msg mid="95"><![CDATA[Quest telah ditambahkan.]]></todo_msg>
      </journal>
      <journal index="2">
         <contents_image>QN_Npc_geraint_Kid.dds</contents_image>
         <destination_pos>13526,n2304</destination_pos>
         <destination_mode>custom:54@4,13526@1</destination_mode>
         <statemark_npcid>2304</statemark_npcid>
         <statemark_type>2</statemark_type>
         <trigger_string />
         <maptool_index />
         <title mid="96"><![CDATA[Returned Gerraint.]]></title>
         <contents mid="97"><![CDATA[<html>Gerraint yang pergi ke Monolith untuk mencari petunjuk tentang Healing Cup telah kembali. Masuklah ke Inside the Monolith dan Bicaralah dengan Gerraint.<BR><BR><FONT color=#086171>Heart of Merkha(Norfe)</FONT><FONT color=#a82424> - Inside the Monolith(Gerraint)</FONT></html>]]></contents>
         <destination mid="98"><![CDATA[Lewat Norfe, pergilah ke Inside the Monolith dan bicara dengan Gerraint]]></destination>
         <todo_msg mid="99"><![CDATA[Lewat Norfe pergilah ke Inside the Monolith lalu bicaralah dengan Gerraint.]]></todo_msg>
      </journal>
      <journal index="3">
         <contents_image>QN_Npc_geraint_Kid.dds</contents_image>
         <destination_pos>54,n2254</destination_pos>
         <destination_mode>custom:</destination_mode>
         <statemark_npcid>2254</statemark_npcid>
         <statemark_type>2</statemark_type>
         <trigger_string />
         <maptool_index />
         <title mid="100"><![CDATA[Dig the Urn's Secret!]]></title>
         <contents mid="101"><![CDATA[<html>Pergilah ke tempat di mana Urn berada di Rubinart's Hideout dan bicaralah dengan Gerraint.<BR><BR><FONT color=#086171>Heart of Merkha(Rubinart's Hideout)</FONT> - <FONT color=#a82424>Gerraint</FONT></html>]]></contents>
         <destination mid="102"><![CDATA[Pergi ke Rubinart's Hideout dan bicara dengan Gerraint]]></destination>
         <todo_msg mid="103"><![CDATA[Pergilah ke Rubinart's Hideout dan bicaralah dengan Gerraint.]]></todo_msg>
      </journal>
      <journal index="4">
         <contents_image>QW_Rubinat_Hideout.dds</contents_image>
         <destination_pos>54,n1813</destination_pos>
         <destination_mode>custom:</destination_mode>
         <statemark_npcid>1813</statemark_npcid>
         <statemark_type>2</statemark_type>
         <trigger_string />
         <maptool_index />
         <title mid="104"><![CDATA[Key to the Ashes.]]></title>
         <contents mid="105"><![CDATA[<html>Gunakan peninggalan Meriendel untuk membuka Meriendel's Urn yang ditinggalkan oleh Rubinart.<BR><BR><FONT color=#086171>Heart of Merkha(Rubinart's Hideout)</FONT> - <FONT color=#a82424>Mysterious Casket</FONT></html>]]></contents>
         <destination mid="106"><![CDATA[Membuka Casket di Rubinart's Hideout]]></destination>
         <todo_msg mid="107"><![CDATA[Pergilah ke Rubinart Hideout dan bukalah Mysterious Casket.]]></todo_msg>
      </journal>
      <journal index="5">
         <contents_image>QW_Rubinat_Hideout.dds</contents_image>
         <destination_pos>54,n2265</destination_pos>
         <destination_mode>custom:</destination_mode>
         <statemark_npcid>2265</statemark_npcid>
         <statemark_type>2</statemark_type>
         <trigger_string />
         <maptool_index />
         <title mid="108"><![CDATA[Rubinart Phantasm.]]></title>
         <contents mid="109"><![CDATA[<html>Setelah membuka Meriendel's Urn, muncullah Rubinart Phantasm. Bicaralah dengannya.<BR><BR><FONT color=#086171>Heart of Merkha(Rubinart's Hideout)</FONT> - <FONT color=#a82424>Rubinart Phantasm</FONT></html>]]></contents>
         <destination mid="110"><![CDATA[Pergi ke Rubinart's Hideout dan bicara dengan Rubinart's Welcome]]></destination>
         <todo_msg mid="111"><![CDATA[Rubinart Hideout dan bicaralah dengan Rubinart's Welcome.]]></todo_msg>
      </journal>
      <journal index="6">
         <contents_image>QN_Npc_geraint_Kid.dds</contents_image>
         <destination_pos>54,n2254</destination_pos>
         <destination_mode>custom:</destination_mode>
         <statemark_npcid>2254</statemark_npcid>
         <statemark_type>3</statemark_type>
         <trigger_string />
         <maptool_index />
         <title mid="166"><![CDATA[Rubinart's Message.]]></title>
         <contents mid="167"><![CDATA[<html>Rubinart meninggalkan informasi yang misterius sebelum mengihlang. Mari sampaikan informasi ini kepada Gerraint.<BR><BR><FONT color=#086171>Heart of Merkha(Rubinart's Hideout)</FONT> - <FONT color=#a82424>Gerraint</FONT></html>]]></contents>
         <destination mid="168"><![CDATA[Pergi ke Rubinart's Hideout dan bicara dengan Gerraint]]></destination>
         <todo_msg mid="169"><![CDATA[Pergilah ke Rubinart Hideout lalu bicaralah dengan Gerraint.]]></todo_msg>
      </journal>
   </journal_data>
   <condition_data>
      <user_level>93:-1</user_level>
      <user_class />
      <prev_quest>9778</prev_quest>
      <have_quest />
      <have_normal_item />
      <complete_mission />
      <npc_favor />
      <have_cash_item />
      <have_daily_quest />
   </condition_data>
</quest>